{
  "applications": "*",
  "changelogDate": "20220824112142",
  "dto": "mapstruct",
  "embedded": false,
  "entityTableName": "taluka",
  "fields": [
    {
      "fieldName": "talukaName",
      "fieldType": "String",
      "fieldValidateRules": ["required"]
    },
    {
      "fieldName": "deleted",
      "fieldType": "Boolean"
    },
    {
      "fieldName": "lgdCode",
      "fieldType": "Long"
    },
    {
      "fieldName": "lastModified",
      "fieldType": "Instant"
    },
    {
      "fieldName": "lastModifiedBy",
      "fieldType": "String"
    }
  ],
  "fluentMethods": true,
  "jpaMetamodelFiltering": true,
  "name": "Taluka",
  "pagination": "pagination",
  "readOnly": false,
  "relationships": [],
  "service": "serviceClass"
}
